datacheck/__init__.py
datacheck/compat.py
datacheck/core.py
datacheck/exceptions.py
datacheck/path.py
datacheck-0.3.0.dist-info/LICENSE
datacheck-0.3.0.dist-info/METADATA
datacheck-0.3.0.dist-info/WHEEL
datacheck-0.3.0.dist-info/top_level.txt
datacheck-0.3.0.dist-info/RECORD
