Metadata-Version: 2.1
Name: datacheck
Version: 0.3.0
Summary: data validation library
Home-page: https://github.com/csdev/datacheck
Author: Christopher Sang
License: MIT
Classifier: Development Status :: 7 - Inactive
Classifier: Intended Audience :: Developers
Classifier: License :: OSI Approved :: MIT License
Classifier: Programming Language :: Python :: 3.7
Classifier: Programming Language :: Python :: 3.8
Classifier: Programming Language :: Python :: 3.9
Classifier: Topic :: Utilities
License-File: LICENSE
Requires-Dist: future (>=0.14.3)
